MANIFEST.in
setup.py
trac_GitolitePlugin.egg-info/PKG-INFO
trac_GitolitePlugin.egg-info/SOURCES.txt
trac_GitolitePlugin.egg-info/dependency_links.txt
trac_GitolitePlugin.egg-info/entry_points.txt
trac_GitolitePlugin.egg-info/top_level.txt
trac_gitolite/__init__.py
trac_gitolite/perm_manager.py
trac_gitolite/perm_policy.py
trac_gitolite/repo_manager.py
trac_gitolite/user_manager.py
trac_gitolite/utils.py
trac_gitolite/templates/admin_repository_gitolite.html
trac_gitolite/templates/admin_repository_permissions.html
trac_gitolite/templates/admin_repository_users.html