Metadata-Version: 1.0
Name: trac-GitolitePlugin
Version: 0.2.4
Summary: UNKNOWN
Home-page: http://trac-hacks.org/wiki/GitolitePlugin
Author: Ethan Jucovy
Author-email: ejucovy@gmail.com
License: BSD
Platform: UNKNOWN
